caf_analysis/__init__.py
caf_analysis/main.py
caf_analysis-1.42.dist-info/METADATA
caf_analysis-1.42.dist-info/WHEEL
caf_analysis-1.42.dist-info/top_level.txt
caf_analysis-1.42.dist-info/RECORD
